easyEmbed/__init__.py
easyEmbed/easyEmbed.py
easyEmbed/embeddings.py
easyEmbed-0.0.4.dist-info/DESCRIPTION.rst
easyEmbed-0.0.4.dist-info/METADATA
easyEmbed-0.0.4.dist-info/RECORD
easyEmbed-0.0.4.dist-info/WHEEL
easyEmbed-0.0.4.dist-info/metadata.json
easyEmbed-0.0.4.dist-info/top_level.txt
embed2all/Embeddings.py
embed2all/__init__.py
embed2all/embed2all.py
