Metadata-Version: 2.0
Name: easyEmbed
Version: 0.0.4
Summary: easyEmbed is a tool for people who use pretrained word embeddings
Home-page: https://github.com/yanaiela/easyEmbed
Author: Yanai Elazar
Author-email: yanaiela@gmail.com
License: UNKNOWN
Download-URL: https://github.com/yanaiela/easyEmbed/archive/0.0.4.tar.gz
Keywords: embedding,word2vec,glove
Platform: UNKNOWN
Classifier: Development Status :: 3 - Alpha
Classifier: Programming Language :: Python :: 2.7
